iotoolz/__init__.py
iotoolz/_abc.py
iotoolz/_chardet.py
iotoolz/_toolz.py
iotoolz/extensions/__init__.py
iotoolz/extensions/_not_implemented.py
iotoolz/extensions/minio.py
iotoolz/extensions/s3.py
iotoolz/file.py
iotoolz/http.py
iotoolz/streams.py
iotoolz/temp.py
iotoolz/utils.py
iotoolz-0.1.0.dist-info/LICENSE
iotoolz-0.1.0.dist-info/WHEEL
iotoolz-0.1.0.dist-info/METADATA
iotoolz-0.1.0.dist-info/RECORD
